mlflow_assistant/__init__.py
mlflow_assistant/cli/__init__.py
mlflow_assistant/cli/commands.py
mlflow_assistant/cli/setup.py
mlflow_assistant/cli/validation.py
mlflow_assistant/core/__init__.py
mlflow_assistant/core/cli.py
mlflow_assistant/core/connection.py
mlflow_assistant/core/core.py
mlflow_assistant/core/provider.py
mlflow_assistant/core/workflow.py
mlflow_assistant/engine/__init__.py
mlflow_assistant/engine/definitions.py
mlflow_assistant/engine/processor.py
mlflow_assistant/engine/tools.py
mlflow_assistant/engine/workflow.py
mlflow_assistant/main.py
mlflow_assistant/providers/__init__.py
mlflow_assistant/providers/base.py
mlflow_assistant/providers/databricks_provider.py
mlflow_assistant/providers/definitions.py
mlflow_assistant/providers/ollama_provider.py
mlflow_assistant/providers/openai_provider.py
mlflow_assistant/providers/utilities.py
mlflow_assistant/utils/__init__.py
mlflow_assistant/utils/config.py
mlflow_assistant/utils/constants.py
mlflow_assistant/utils/definitions.py
mlflow_assistant/utils/exceptions.py
mlflow_assistant-0.1.5.dist-info/METADATA
mlflow_assistant-0.1.5.dist-info/WHEEL
mlflow_assistant-0.1.5.dist-info/entry_points.txt
mlflow_assistant-0.1.5.dist-info/licenses/LICENCE
mlflow_assistant-0.1.5.dist-info/RECORD
