Metadata-Version: 2.4
Name: mlflow-assistant
Version: 0.1.5
Summary: An MLflow plugin that enables natural language conversations with your MLflow server using LLM providers like OpenAI and Ollama.
License: Apache-2.0
License-File: LICENCE
Author: Hugo Carvalho
Author-email: hugodanielsilvacarvalho.hc@gmail.com
Requires-Python: >=3.12.4,<4.0
Classifier: License :: OSI Approved :: Apache Software License
Classifier: Programming Language :: Python :: 3
Classifier: Programming Language :: Python :: 3.13
Classifier: Programming Language :: Python :: 3.14
Provides-Extra: dev
Requires-Dist: black (>=22.0.0) ; extra == "dev"
Requires-Dist: click (>=8.0.0)
Requires-Dist: databricks-langchain (>=0.6.0,<0.7.0)
Requires-Dist: isort (>=5.0.0) ; extra == "dev"
Requires-Dist: langchain-core (>=0.3.72,<0.4.0)
Requires-Dist: langchain-ollama (==0.3.8)
Requires-Dist: langchain-openai (>=0.3.30,<0.4.0)
Requires-Dist: langgraph (==0.2.53)
Requires-Dist: mlflow (>=2.21.0,<3.0.0)
Requires-Dist: pytest (>=7.0.0) ; extra == "dev"
Requires-Dist: python-dotenv
Requires-Dist: pyyaml (>=6.0)
Requires-Dist: requests (>=2.25.0)
Requires-Dist: scipy (>=1.16.0,<2.0.0)
